llm_tools_kit.py
llm_tools_kit-0.1.dist-info/licenses/LICENSE
llm_tools_kit-0.1.dist-info/METADATA
llm_tools_kit-0.1.dist-info/WHEEL
llm_tools_kit-0.1.dist-info/entry_points.txt
llm_tools_kit-0.1.dist-info/top_level.txt
llm_tools_kit-0.1.dist-info/RECORD
