Metadata-Version: 2.4
Name: llm-tools-kit
Version: 0.1
Summary: wrapper for cased-kit's code analysis toolset
Author: Kyle Gruel
License-Expression: Apache-2.0
Project-URL: Homepage, https://github.com/kgruel/llm-tools-kit
Project-URL: Changelog, https://github.com/kgruel/llm-tools-kit/releases
Project-URL: Issues, https://github.com/kgruel/llm-tools-kit/issues
Project-URL: CI, https://github.com/kgruel/llm-tools-kit/actions
Requires-Python: >=3.9
License-File: LICENSE
Requires-Dist: cased-kit>=0.1.4
Requires-Dist: llm>=0.26
Provides-Extra: test
Requires-Dist: pytest; extra == "test"
Requires-Dist: llm-echo>=0.3a1; extra == "test"
Dynamic: license-file
